.bzrignore
setup.cfg
setup.py
docs/CREDITS.txt
docs/HISTORY.txt
docs/LICENSE.GPL
docs/LICENSE.txt
docs/README.txt
docs/TODO.txt
gf/__init__.py
gf.recipe.bzr.egg-info/PKG-INFO
gf.recipe.bzr.egg-info/SOURCES.txt
gf.recipe.bzr.egg-info/dependency_links.txt
gf.recipe.bzr.egg-info/entry_points.txt
gf.recipe.bzr.egg-info/namespace_packages.txt
gf.recipe.bzr.egg-info/requires.txt
gf.recipe.bzr.egg-info/top_level.txt
gf.recipe.bzr.egg-info/zip-safe
gf/recipe/__init__.py
gf/recipe/bzr/__init__.py
gf/recipe/bzr/bzr.py
gf/recipe/bzr/bzr_strict.py