Metadata-Version: 1.0
Name: gf.recipe.bzr
Version: 1.0rc8
Summary: Buildout recipe to download bazaar branches
Home-page: http://launchpad.net/gf.recipe.bzr
Author: Balazs Ree
Author-email: ree@greenfinity.hu
License: GPL
Platform: UNKNOWN
Classifier: Development Status :: 3 - Alpha
Classifier: Intended Audience :: Developers
Classifier: Programming Language :: Python
Classifier: Topic :: Software Development :: Libraries :: Python Modules
